QPT_SDK/__init__.py
QPT_SDK/loc.py
QPT_SDK-1.0.1.dist-info/LICENSE
QPT_SDK-1.0.1.dist-info/METADATA
QPT_SDK-1.0.1.dist-info/WHEEL
QPT_SDK-1.0.1.dist-info/top_level.txt
QPT_SDK-1.0.1.dist-info/RECORD
