Metadata-Version: 2.1
Name: QPT-SDK
Version: 1.0.1
Summary: QPT_SDK占位文件夹
Home-page: https://github.com/GT-ZhangAcer/QPT
Author: GT-ZhangAcer
Author-email: zhangacer@foxmail.com
License: LGPL
License-File: LICENSE
